NasrPy/__init__.py
DevDec-0.2.dist-info/METADATA
DevDec-0.2.dist-info/WHEEL
DevDec-0.2.dist-info/top_level.txt
DevDec-0.2.dist-info/RECORD
