Metadata-Version: 2.1
Name: DevDec
Version: 0.2
Summary: This is the best encryption library for Devil
Author: Devil
Classifier: Programming Language :: Python :: 3
